odoo/addons/sale_order_partner_membership/LICENSE
odoo/addons/sale_order_partner_membership/README.rst
odoo/addons/sale_order_partner_membership/__init__.py
odoo/addons/sale_order_partner_membership/__manifest__.py
odoo/addons/sale_order_partner_membership/i18n/de.po
odoo/addons/sale_order_partner_membership/i18n/de_CH.po
odoo/addons/sale_order_partner_membership/images/screen.png
odoo/addons/sale_order_partner_membership/models/__init__.py
odoo/addons/sale_order_partner_membership/models/product_template.py
odoo/addons/sale_order_partner_membership/models/sale_order.py
odoo/addons/sale_order_partner_membership/static/description/icon.png
odoo/addons/sale_order_partner_membership/static/description/index.html
odoo/addons/sale_order_partner_membership/tests/TEST_INSTRUCTIONS.rst
odoo/addons/sale_order_partner_membership/views/product_template.xml
odoo/addons/sale_order_partner_membership/views/sale_order.xml
odoo_addon_sale_order_partner_membership-18.0.1.0.0.dist-info/METADATA
odoo_addon_sale_order_partner_membership-18.0.1.0.0.dist-info/WHEEL
odoo_addon_sale_order_partner_membership-18.0.1.0.0.dist-info/top_level.txt
odoo_addon_sale_order_partner_membership-18.0.1.0.0.dist-info/RECORD
