Metadata-Version: 2.1
Name: odoo-addon-sale_order_partner_membership
Version: 18.0.1.0.0
Requires-Python: >=3.10
Requires-Dist: odoo-addon-partner_type_membership==18.0.*
Requires-Dist: odoo==18.0.*
Summary: Set membership address on sale order.
Home-page: https://www.mint-system.ch/
License: AGPL-3
Author: Mint System GmbH
Classifier: Programming Language :: Python
Classifier: Framework :: Odoo
Classifier: Framework :: Odoo :: 18.0
Classifier: License :: OSI Approved :: GNU Affero General Public License v3
